trading212_api-0.1.dist-info/DESCRIPTION.rst
trading212_api-0.1.dist-info/METADATA
trading212_api-0.1.dist-info/RECORD
trading212_api-0.1.dist-info/WHEEL
trading212_api-0.1.dist-info/metadata.json
trading212_api-0.1.dist-info/top_level.txt
trading212api/__init__.py
trading212api/_internal_utils.py
trading212api/api.py
trading212api/datastruct.py
trading212api/exceptions.py
