Metadata-Version: 2.0
Name: trading212-api
Version: 0.1
Summary: Package to interact with the broker service Trading212
Home-page: https://github.com/federico123579/Trading212api
Author: Federico Lolli
Author-email: federico123579@gmail.com
License: MIT
Keywords: trading api
Platform: UNKNOWN
Classifier: Development Status :: 3 - Alpha
Classifier: Environment :: Web Environment
Classifier: Intended Audience :: Developers
Classifier: License :: OSI Approved :: MIT License
Classifier: Programming Language :: Python :: 3.6
Classifier: Topic :: Software Development :: User Interfaces
Requires-Dist: requests
